Exam_2021/2d/AC_Controller.v
`timescale 1ns / 100ps


module AC_Controller (
    input  wire [0:0] clk,
    input  wire [0:0] reset,
	input  wire [0:0] power,
	input  wire [1:0] temp_comp,
	output  [1:0] action,
	output   [1:0] state_display
    );
    
  // Add your FSM implementation here...
    
    
    reg [1:0] curr_state,next_state;
    
    localparam 
    off=2'd0,
    decrease=2'd1,
    increase=2'd2,
    idle=2'd3;
    
    always @(posedge clk) begin
        if(reset) begin
            curr_state<=off;
        
        end else begin
            curr_state<=next_state;
        
        
        end
    end
    
    
    
    
    always @(*) begin
        next_state=curr_state;
        if(power) begin
        case(curr_state)
            off: next_state= (temp_comp==2'b10 && power) ? decrease :  (temp_comp==2'b01 && power) ? increase : (temp_comp==2'b00 && power) ? idle: !power ? off :curr_state;
            decrease: next_state= (temp_comp==2'b01 && power) ? increase : (temp_comp==2'b00 && power) ? idle : !power ? off :curr_state ;
            increase: next_state= (temp_comp==2'b10 && power) ? decrease : (temp_comp==2'b00 && power) ? idle : !power ? off :curr_state;
            idle: next_state= (temp_comp==2'b10) ? decrease :  (temp_comp==2'b01) ? increase :!power ? off :curr_state;
            default: next_state=curr_state;
        endcase
        end
    end
    
    assign state_display=curr_state;
    assign action= (curr_state==off) ? 2'b11 : (curr_state==decrease) ? 2'b01 : (curr_state==increase) ? 2'b10 : 2'b00;
    
    
    
endmodule

Exam_2021/2d/src/AC_Controller_ref.v
`timescale 1ns / 100ps


module AC_Controller_ref (
    input  wire [0:0] clk,
    input  wire [0:0] reset,
	input  wire [0:0] power,
	input  wire [1:0] temp_comp,
	output  [1:0] action,
	output   [1:0] state_display
    );
    
  // Add your FSM implementation here...
    
    
    reg [1:0] curr_state,next_state;
    
    localparam 
    off=2'd0,
    decrease=2'd1,
    increase=2'd2,
    idle=2'd3;
    
    always @(posedge clk) begin
        if(reset) begin
            curr_state<=off;
        
        end else begin
            curr_state<=next_state;
        
        
        end
    end
    
    
    
    
    always @(*) begin
        next_state=curr_state;
        if(power) begin
        case(curr_state)
            off: next_state= (temp_comp==2'b10 && power) ? decrease :  (temp_comp==2'b01 && power) ? increase : (temp_comp==2'b00 && power) ? idle: !power ? off :curr_state;
            decrease: next_state= (temp_comp==2'b01 && power) ? increase : (temp_comp==2'b00 && power) ? idle : !power ? off :curr_state ;
            increase: next_state= (temp_comp==2'b10 && power) ? decrease : (temp_comp==2'b00 && power) ? idle : !power ? off :curr_state;
            idle: next_state= (temp_comp==2'b10) ? decrease :  (temp_comp==2'b01) ? increase :!power ? off :curr_state;
            default: next_state=curr_state;
        endcase
        end
    end
    
    assign state_display=curr_state;
    assign action= (curr_state==off) ? 2'b11 : (curr_state==decrease) ? 2'b01 : (curr_state==increase) ? 2'b10 : 2'b00;
    
    
    
endmodule

Exam_2021/2d/src/Test_tb.v
`timescale 1ns/1ns
`include "AC_Controller.v"
`include "AC_Controller_ref.v"
// COMPILE THE CODE WITH THE FOLLOWING COMMAND:
// "iverilog -o compiled.vvp Test_tb.v"

// COMPILE THE SIMULATION WITH THE FOLLOWING COMMAND:
// "vvp compiled.vvp"

// SEE THE SIMULATION WITH THE FOLLOWING COMMAND:
// "gtkwave gtk_sim.vcd"

module Test_tb;

       reg clk = 0;
    reg reset = 0;
    reg power = 0;
    reg [1:0] temp_comp = 2'b00;
    
    wire [1:0] action;
    wire [1:0] state_display;
    wire [1:0] action_ref;
    wire [1:0] state_display_ref;
    
    // Instantiate the AC_Controller FSM
    AC_Controller_ref AC_Controller_ref_inst (
        .clk(clk),
        .reset(reset),
        .power(power),
        .temp_comp(temp_comp),
        .action(action_ref),
        .state_display(state_display_ref)
    );
                
    AC_Controller AC_Controller_inst (
        .clk(clk),
        .reset(reset),
        .power(power),
        .temp_comp(temp_comp),
        .action(action),
        .state_display(state_display)
    );

        // Check outputs at every positive edge of the clock
        reg pass = 1; // Indicator for whether outputs match across all cycles
        always @(posedge clk) begin
                if (action !== action_ref | state_display !== state_display_ref) begin
                        pass = 0;
                end
        end

        // Task to finish simulation and print result
        reg [7:0] test_nr = 'd1; // Indicator for whether outputs match across all cycles
        task test_evalutation();
                begin
                if (pass) begin
                        $display("->TEST %d: PASSED",test_nr);
                end else begin
                        $display("->TEST %d: FAILED",test_nr);
                        finish_test(); // Terminate the simulation early on failure
                end
                test_nr = test_nr + 'd1;
                end
        endtask

        // Task to finish simulation and print result
        task finish_test();
                begin
                if (pass) begin
                        $display("\nFINAL EVALUATION: PASSED\n");
                end else begin
                        $display("\nFINAL EVALUATION: FAILED\n");
                end
                #40;
                $display("Test Bench TERMINATED at time: %d [Ns].",$time);
                $finish;
                end
        endtask

        // Clock generation
        always #10 clk = ~clk;
        
        initial begin
	        $dumpfile("src/gtk_sim.vcd");
   	        $dumpvars(0, Test_tb);

                $display("Test Bench Started!!!!!");
// <<INITIALIZE INPUT SIGNALS>>
        clk = 0;
        reset = 0;
        power = 0;
        temp_comp = 2'b00;

        // <<RESET>>
        reset = 1; #40;
        reset = 0; #20;

        // <<TEST SEQUENCE 1: Power Off (Initial State)>>
        power = 0;
        temp_comp = 2'b00;
        #20;

        // <<TEST SEQUENCE 2: Power On, Temperature is Equal (Idle State)>>
        power = 1;
        temp_comp = 2'b00;
        #20;

        // <<TEST SEQUENCE 3: Power On, Temperature Higher (Decrease State)>>
        power = 1;
        temp_comp = 2'b10;
        #20;

        // <<TEST SEQUENCE 4: Power On, Temperature Lower (Increase State)>>
        power = 1;
        temp_comp = 2'b01;
        #20;

        // <<TEST SEQUENCE 5: Power On, Temperature Equal (Transition to Idle State)>>
        power = 1;
        temp_comp = 2'b00;
        #20;

        // <<TEST SEQUENCE 6: Power Off (Return to Off State)>>
        power = 0;
        temp_comp = 2'b00;
        #20;

        // <<TEST SEQUENCE 7: Power On, Temperature Higher (Transition Directly to Decrease from Off)>>
        power = 1;
        temp_comp = 2'b10;
        #20;

        // <<TEST SEQUENCE 8: Power On, Temperature Lower (Transition to Increase)>>
        power = 1;
        temp_comp = 2'b01;
        #20;

        // <<TEST SEQUENCE 9: Power Off during Decrease (Immediate transition to Off)>>
        power = 0;
        temp_comp = 2'b10;
        #20;

        // <<TEST SEQUENCE 10: Power On, Temperature Equal (From Off to Idle State)>>
        power = 1;
        temp_comp = 2'b00;
        #20;

        
        test_evalutation();
        // <<RESET>>
    reset = 1; #40;
    reset = 0; #20;

    // <<TEST SEQUENCE 1: Power On, Temperature Lower (Transition to Increase)>>
    power = 1;
    temp_comp = 2'b01;
    #20;

    // <<TEST SEQUENCE 2: Temperature Remains Lower (Stay in Increase)>>
    power = 1;
    temp_comp = 2'b01;
    #20;

    // <<TEST SEQUENCE 3: Temperature Becomes Equal (Transition to Idle)>>
    power = 1;
    temp_comp = 2'b00;
    #20;

    // <<TEST SEQUENCE 4: Power Off While Idle (Transition to Off)>>
    power = 0;
    temp_comp = 2'b00;
    #20;

    // <<TEST SEQUENCE 5: Power On, Temperature Higher (Transition to Decrease)>>
    power = 1;
    temp_comp = 2'b10;
    #20;

    // <<TEST SEQUENCE 6: Temperature Becomes Lower (Transition to Increase)>>
    power = 1;
    temp_comp = 2'b01;
    #20;

    // <<TEST SEQUENCE 7: Temperature Remains Higher (Transition to Decrease)>>
    power = 1;
    temp_comp = 2'b10;
    #20;

    // <<TEST SEQUENCE 8: Temperature Becomes Equal Again (Transition to Idle)>>
    power = 1;
    temp_comp = 2'b00;
    #20;

    // <<TEST SEQUENCE 9: Power Off While in Decrease State (Transition to Off)>>
    power = 0;
    temp_comp = 2'b10;
    #20;

    // <<TEST SEQUENCE 10: Power On, Immediate Temperature Equal (Transition Directly to Idle)>>
    power = 1;
    temp_comp = 2'b00;
    #20;

        test_evalutation();
//      <<<<FINISH>>>>
        finish_test();

        end
endmodule

Exam_2021/2d/src/gtk_sim.vcd
$date
	Fri Aug 16 22:31:35 2024
$end
$version
	Icarus Verilog
$end
$timescale
	100ps
$end
$scope module Test_tb $end
$var wire 2 ! state_display_ref [1:0] $end
$var wire 2 " state_display [1:0] $end
$var wire 2 # action_ref [1:0] $end
$var wire 2 $ action [1:0] $end
$var reg 1 % clk $end
$var reg 1 & pass $end
$var reg 1 ' power $end
$var reg 1 ( reset $end
$var reg 2 ) temp_comp [1:0] $end
$var reg 8 * test_nr [7:0] $end
$scope module AC_Controller_inst $end
$var wire 1 % clk $end
$var wire 1 ' power $end
$var wire 1 ( reset $end
$var wire 2 + state_display [1:0] $end
$var wire 2 , temp_comp [1:0] $end
$var wire 2 - action [1:0] $end
$var parameter 2 . decrease $end
$var parameter 2 / idle $end
$var parameter 2 0 increase $end
$var parameter 2 1 off $end
$var reg 2 2 curr_state [1:0] $end
$var reg 2 3 next_state [1:0] $end
$upscope $end
$scope module AC_Controller_ref_inst $end
$var wire 1 % clk $end
$var wire 1 ' power $end
$var wire 1 ( reset $end
$var wire 2 4 state_display [1:0] $end
$var wire 2 5 temp_comp [1:0] $end
$var wire 2 6 action [1:0] $end
$var parameter 2 7 decrease $end
$var parameter 2 8 idle $end
$var parameter 2 9 increase $end
$var parameter 2 : off $end
$var reg 2 ; curr_state [1:0] $end
$var reg 2 < next_state [1:0] $end
$upscope $end
$scope task finish_test $end
$upscope $end
$scope task test_evalutation $end
$upscope $end
$upscope $end
$enddefinitions $end
$comment Show the parameter values. $end
$dumpall
b0 :
b10 9
b11 8
b1 7
b0 1
b10 0
b11 /
b1 .
$end
#0
$dumpvars
bx <
bx ;
bx 6
b0 5
bx 4
bx 3
bx 2
bx -
b0 ,
bx +
b1 *
b0 )
1(
0'
1&
0%
bx $
bx #
bx "
bx !
$end
#100
b0 <
b11 #
b11 6
b0 3
b11 $
b11 -
b0 !
b0 4
b0 ;
b0 "
b0 +
b0 2
1%
#200
0%
#300
1%
#400
0%
0(
#500
1%
#600
0%
#700
1%
#800
b11 3
b11 <
0%
1'
#900
b0 #
b0 6
b0 $
b0 -
b11 !
b11 4
b11 ;
b11 "
b11 +
b11 2
1%
#1000
b1 3
b1 <
0%
b10 )
b10 ,
b10 5
#1100
b1 $
b1 -
b1 #
b1 6
b1 "
b1 +
b1 2
b1 !
b1 4
b1 ;
1%
#1200
b10 3
b10 <
0%
b1 )
b1 ,
b1 5
#1300
b10 #
b10 6
b10 $
b10 -
b10 !
b10 4
b10 ;
b10 "
b10 +
b10 2
1%
#1400
b11 3
b11 <
0%
b0 )
b0 ,
b0 5
#1500
b0 $
b0 -
b0 #
b0 6
b11 "
b11 +
b11 2
b11 !
b11 4
b11 ;
1%
#1600
0%
0'
#1700
1%
#1800
b1 3
b1 <
0%
b10 )
b10 ,
b10 5
1'
#1900
b1 $
b1 -
b1 #
b1 6
b1 "
b1 +
b1 2
b1 !
b1 4
b1 ;
1%
#2000
b10 3
b10 <
0%
b1 )
b1 ,
b1 5
#2100
b10 #
b10 6
b10 $
b10 -
b10 !
b10 4
b10 ;
b10 "
b10 +
b10 2
1%
#2200
0%
b10 )
b10 ,
b10 5
0'
#2300
1%
#2400
b11 3
b11 <
0%
b0 )
b0 ,
b0 5
1'
#2500
b0 #
b0 6
b0 $
b0 -
b11 !
b11 4
b11 ;
b11 "
b11 +
b11 2
1%
#2600
0%
1(
b10 *
#2700
b11 3
b11 $
b11 -
b11 <
b11 #
b11 6
b0 "
b0 +
b0 2
b0 !
b0 4
b0 ;
1%
#2800
0%
#2900
1%
#3000
0%
0(
#3100
b0 $
b0 -
b0 #
b0 6
b11 "
b11 +
b11 2
b11 !
b11 4
b11 ;
1%
#3200
b10 3
b10 <
0%
b1 )
b1 ,
b1 5
#3300
b10 #
b10 6
b10 $
b10 -
b10 !
b10 4
b10 ;
b10 "
b10 +
b10 2
1%
#3400
0%
#3500
1%
#3600
b11 3
b11 <
0%
b0 )
b0 ,
b0 5
#3700
b0 #
b0 6
b0 $
b0 -
b11 !
b11 4
b11 ;
b11 "
b11 +
b11 2
1%
#3800
0%
0'
#3900
1%
#4000
b1 3
b1 <
0%
b10 )
b10 ,
b10 5
1'
#4100
b1 #
b1 6
b1 $
b1 -
b1 !
b1 4
b1 ;
b1 "
b1 +
b1 2
1%
#4200
b10 3
b10 <
0%
b1 )
b1 ,
b1 5
#4300
b10 $
b10 -
b10 #
b10 6
b10 "
b10 +
b10 2
b10 !
b10 4
b10 ;
1%
#4400
b1 3
b1 <
0%
b10 )
b10 ,
b10 5
#4500
b1 #
b1 6
b1 $
b1 -
b1 !
b1 4
b1 ;
b1 "
b1 +
b1 2
1%
#4600
b11 3
b11 <
0%
b0 )
b0 ,
b0 5
#4700
b0 $
b0 -
b0 #
b0 6
b11 "
b11 +
b11 2
b11 !
b11 4
b11 ;
1%
#4800
0%
b10 )
b10 ,
b10 5
0'
#4900
1%
#5000
0%
b0 )
b0 ,
b0 5
1'
#5100
1%
#5200
0%
b11 *
