Resit_2024/2e/spi_fsm.v
module spi_fsm( input clk,
                input reset,
                input [1:0] mode,
                input cs,
                input sclk,
                output sample,
                output shift);

    parameter RESET = 'd0;
    parameter CS = 'd1;
    parameter MODE = 'd2;
    parameter FIRST1 = 'd3;
    parameter FIRST3 = 'd4;
    parameter LAST1 = 'd5;
    parameter LAST3 = 'd6;
    parameter WAIT_LO1 = 'd7;
    parameter WAIT_LO0 = 'd8;
    parameter WAIT_LO2 = 'd9;
    parameter WAIT_LO3 = 'd10;
    parameter WAIT_HI0 = 'd11;
    parameter WAIT_HI1 = 'd12;
    parameter WAIT_HI2 = 'd13;
    parameter WAIT_HI3 = 'd14;
    parameter SHIFT0 = 'd15;
    parameter SHIFT1 = 'd16;
    parameter SHIFT2 = 'd17;
    parameter SHIFT3 = 'd18;
    parameter SAMPLE0 = 'd19;
    parameter SAMPLE1 = 'd20;
    parameter SAMPLE2 = 'd21;
    parameter SAMPLE3 = 'd22;

    reg [4:0] state, state_next;
    assign sample = (state == SAMPLE0 | state == SAMPLE1 | state == SAMPLE2 | state == SAMPLE3 );
    assign shift = (state == SHIFT0 | state == SHIFT1 | state == SHIFT2 | state == SHIFT3 );

    always @(posedge clk)begin
        if(reset) begin
            state <= RESET;
        end else begin
            state <= state_next;
        end
    end

    always @(*)begin
        state_next = state;

        case(state)
            
            RESET: begin
                state_next = CS;
            end
            
            CS: begin
                if(cs == 1) begin
                    state_next = MODE;
                end
            end

            MODE: begin
                if(mode == 'b01 && cs == 0 && sclk == 0) begin
                    state_next = FIRST1;
                end else if(mode == 'b00 && cs == 0 && sclk == 0) begin
                    state_next = WAIT_LO0;
                end else if(mode == 'b11 && cs == 0 && sclk == 1) begin
                    state_next = FIRST3;
                end else if(mode == 'b10 && cs == 0 && sclk == 1) begin
                    state_next = WAIT_HI2;
                end
            end

            FIRST1: state_next = (sclk == 1)? WAIT_HI1:state ;
            WAIT_HI1: state_next = (sclk == 0)? SAMPLE1:state ;
            SAMPLE1: state_next = WAIT_HI1;
            WAIT_LO1: begin
                if(cs == 0 && sclk == 1) begin
                    state_next = SHIFT1;
                end else if(cs == 1) begin
                    state_next = LAST1;
                end
            end
            SHIFT1: state_next = WAIT_HI1;
            LAST1: state_next = (cs == 1)? MODE:state ;
            

            WAIT_LO0: begin
                if(sclk == 1 && cs == 0) begin
                    state_next = SAMPLE0;
                end else if(cs == 1) begin
                    state_next = MODE;
                end
            end
            SAMPLE0: state_next = WAIT_HI0;
            WAIT_HI0: state_next = (sclk == 0)? SHIFT0:state ;
            SHIFT0: state_next = WAIT_LO0;


            FIRST3: state_next = (sclk == 0)? WAIT_LO3:state ;
            WAIT_LO3: state_next = (sclk == 1)? SAMPLE3:state ;
            SAMPLE3: state_next = WAIT_HI3;
            WAIT_HI3:  begin
                if(cs == 0 && sclk == 0) begin
                    state_next = SHIFT3;
                end else if(cs == 1) begin
                    state_next = LAST3;
                end
            end
            SHIFT3: state_next = WAIT_LO3;
            LAST3: state_next = (cs == 1)? MODE:state ;
            

            WAIT_HI2: begin
                if(sclk == 0 && cs == 0) begin
                    state_next = SAMPLE2;
                end else if(cs == 1) begin
                    state_next = MODE;
                end
            end
            SAMPLE2: state_next = WAIT_LO2;
            WAIT_LO2: state_next = (sclk == 1)? SHIFT2:state ;
            SHIFT2: state_next = WAIT_HI2;

            default: begin 
                state_next = RESET;
            end
        endcase   
    end
endmodule

Resit_2024/2e/src/spi_fsm_ref.v
module spi_fsm_ref(
    input wire clk,
    input wire reset,
    input wire [1:0] mode,
    input wire cs,
    input wire sclk,
    output reg shift,
    output reg sample
);

localparam rst = 0;
localparam check_cs_hi =1;
localparam mode_select = 2;
localparam first1 = 3;
localparam first3 =4;
localparam last1 = 5;
localparam last3 = 6;
localparam wait1lo = 7;
localparam wait0lo = 8;
localparam wait2lo = 9;
localparam wait3lo = 10;
localparam wait0hi = 11;
localparam wait1hi = 12;
localparam wait2hi = 13;
localparam wait3hi = 14;
localparam shift0 = 15;
localparam shift1 = 16;
localparam shift2 = 17;
localparam shift3 = 18;
localparam sample0 = 19;
localparam sample1 = 20;
localparam sample2 = 21;
localparam sample3 = 22;

reg [4:0] state_r, state_nxt;

always @(posedge clk)begin
    if(reset == 1)begin
        state_r <= rst; // check
    end else begin
        state_r <= state_nxt;
    end
end

always @(*)begin
    state_nxt = state_r;
    case(state_r)
        check_cs_hi: begin
            if(cs == 1'b1) state_nxt = mode_select;
        end
        mode_select: begin
            if(mode == 2'b01 && cs == 1'b0 && sclk == 1'b0) state_nxt = first1;
            else if(mode == 2'b00 && cs == 1'b0 && sclk == 1'b0) state_nxt = wait0lo;
            else if(mode == 2'b11 && cs == 1'b0 && sclk == 1'b1) state_nxt = first3;
            else if(mode == 2'b10 && cs == 1'b0 && sclk == 1'b1) state_nxt = wait2hi;
        end
        first1: begin
            if(sclk == 1'b1) state_nxt = wait1hi;
        end
        first3: begin
            if(sclk == 1'b0) state_nxt = wait3lo;
        end
        last1: begin
            state_nxt = mode_select;
        end
        last3: begin
            state_nxt = mode_select;
        end
         wait1lo:begin
            if(sclk == 1'b1 && cs == 1'b0) state_nxt = shift1;
            else if(cs == 1'b1) state_nxt = last1;
         end
 wait0lo: begin
    if(sclk == 1'b1 && cs == 1'b0) state_nxt = sample0;
    else if(cs == 1'b1) state_nxt = mode_select;
 end
 wait2lo:begin
    if(sclk == 1'b1) state_nxt = shift2;
 end
 wait3lo:begin
    if(sclk == 1'b1) state_nxt = sample3;
 end
 wait0hi:begin
    if(sclk == 1'b0) state_nxt = shift0;
 end
wait1hi:begin
    if(sclk == 1'b0) state_nxt = sample1;
end
wait2hi:begin
    if(cs == 1'b1) state_nxt = mode_select;
    else if(sclk == 1'b0 && cs == 1'b0) state_nxt = sample2;
end
 wait3hi:begin
    if(cs == 1'b1) state_nxt = last3;
    else if(sclk == 1'b0 && cs == 1'b0) state_nxt = shift3;
 end
 shift0:begin
    state_nxt = wait0lo;
 end
 shift1:begin
    state_nxt = wait1hi;
 end
 shift2:begin
    state_nxt = wait2hi;
 end
 shift3:begin
    state_nxt = wait3lo;
 end
 sample0:begin
    state_nxt = wait0hi;
 end
 sample1:begin
    state_nxt = wait1lo;
 end
 sample2:begin
    state_nxt = wait2lo;
 end
 sample3:begin
    state_nxt = wait3hi;
 end
 default:begin
    state_nxt = check_cs_hi;
 end
    endcase
    
    
end

always @(*)begin
    case(state_r)
        shift1: shift = 1;
        last1: shift =1;
        shift0: shift = 1;
        shift3: shift = 1;
        last3: shift = 1;
        shift2: shift = 1;
        default: shift = 0;
    endcase
end

always @(*)begin
    case(state_r)
        sample1: sample = 1;
        sample0: sample = 1;
        sample3: sample = 1;
        sample2: sample = 1;
        default: sample = 0;
    endcase
end

endmodule

Resit_2024/2e/src/Test_tb.v
`timescale 1ns/1ns
`include "spi_fsm_ref.v"
`include "spi_fsm.v"

// COMPILE THE CODE WITH THE FOLLOWING COMMAND:
// "iverilog -o compiled.vvp Test_tb.v"

// COMPILE THE SIMULATION WITH THE FOLLOWING COMMAND:
// "vvp compiled.vvp"

// SEE THE SIMULATION WITH THE FOLLOWING COMMAND:
// "gtkwave gtk_sim.vcd"

module Test_tb;

        reg clk = 0;
        reg reset = 0;
        reg [1:0] mode = 2'b00;
        reg cs = 1;
        reg sclk = 0;

        wire shift;
        wire sample;
        wire shift_ref;
        wire sample_ref;

        spi_fsm_ref spi_fsm_ref_inst(
            .clk(clk),
            .reset(reset),
            .mode(mode),
            .cs(cs),
            .sclk(sclk),
            .shift(shift_ref),
            .sample(sample_ref)
        );

        spi_fsm spi_fsm_inst(
            .clk(clk),
            .reset(reset),
            .mode(mode),
            .cs(cs),
            .sclk(sclk),
            .shift(shift),
            .sample(sample)
        );

        // Check outputs at every positive edge of the clock
        reg pass = 1; // Indicator for whether outputs match across all cycles
        always @(posedge clk) begin
                if (shift !== shift_ref || sample !== sample_ref) begin
                        if($time > 20) begin
                                pass = 0;
                        end
                end
        end

        // Task to finish simulation and print result
        reg [7:0] test_nr = 1; // Indicator for whether outputs match across all cycles
        task test_evalutation();
                begin
                if (pass) begin
                        $display("->TEST %d: PASSED",test_nr);
                end else begin
                        $display("->TEST %d: FAILED",test_nr);
                        finish_test(); // Terminate the simulation early on failure
                end
                test_nr = test_nr + 1;
                end
        endtask

        // Task to finish simulation and print result
        task finish_test();
                begin
                if (pass) begin
                        $display("\nFINAL EVALUATION: PASSED\n");
                end else begin
                        $display("\nFINAL EVALUATION: FAILED\n");
                end
                #40;
                $display("Test Bench TERMINATED at time: %d [Ns].",$time);
                $finish;
                end
        endtask

        // Clock generation
        always #10 clk = ~clk;
        
        // SCLK toggle for testing
        always #15 sclk = ~sclk;

        initial begin
	        $dumpfile("src/gtk_sim.vcd");
   	        $dumpvars(0, Test_tb);

                $display("Test Bench Started!!!!!");

// 	        <<INITIALIZE INPUT INS>>
                clk = 1;
                reset = 0;
                mode = 2'b00;
                cs = 1;
                sclk = 0;
                        
// 	        <<RESET>>
                reset = 1; #40;
                reset = 0; #20;

// 	        <<TEST SEQUENCE 1: SPI Mode 0, Check Shift and Sample>>
                mode = 2'b00;   // SPI Mode 0
                cs = 0;         // Enable CS
                #30;            // Wait for setup
                cs = 1;         // Disable CS
                #40;
                test_evalutation();

// 	        <<TEST SEQUENCE 2: SPI Mode 1, Check Shift and Sample>>
                mode = 2'b01;   // SPI Mode 1
                cs = 0;         // Enable CS
                #30;            // Wait for setup
                cs = 1;         // Disable CS
                #40;
                test_evalutation();

// 	        <<TEST SEQUENCE 3: SPI Mode 2, Check Shift and Sample>>
                mode = 2'b10;   // SPI Mode 2
                cs = 0;         // Enable CS
                #30;            // Wait for setup
                cs = 1;         // Disable CS
                #40;
                test_evalutation();

// 	        <<TEST SEQUENCE 4: SPI Mode 3, Check Shift and Sample>>
                mode = 2'b11;   // SPI Mode 3
                cs = 0;         // Enable CS
                #30;            // Wait for setup
                cs = 1;         // Disable CS
                #40;
                test_evalutation();

// 	        <<TEST SEQUENCE 5: Test Full Transaction in Mode 0>>
                reset = 1; #40; reset = 0; // Reset
                mode = 2'b00;   // SPI Mode 0
                cs = 0;         // Enable CS
                sclk = 0;       // Start with SCLK low
                #20;
                sclk = 1;       // SCLK rising edge
                #20;
                sclk = 0;       // SCLK falling edge
                #20;
                cs = 1;         // Disable CS
                #40;
                test_evalutation();

// 	        <<TEST SEQUENCE 6: Test Full Transaction in Mode 1>>
                reset = 1; #40; reset = 0; // Reset
                mode = 2'b01;   // SPI Mode 1
                cs = 0;         // Enable CS
                sclk = 1;       // Start with SCLK high
                #20;
                sclk = 0;       // SCLK falling edge
                #20;
                sclk = 1;       // SCLK rising edge
                #20;
                cs = 1;         // Disable CS
                #40;
                test_evalutation();

//      <<<<FINISH>>>>
        finish_test();

        end
endmodule

Resit_2024/2e/src/gtk_sim.vcd
$date
	Mon Aug 19 19:30:09 2024
$end
$version
	Icarus Verilog
$end
$timescale
	1ns
$end
$scope module Test_tb $end
$var wire 1 ! shift_ref $end
$var wire 1 " shift $end
$var wire 1 # sample_ref $end
$var wire 1 $ sample $end
$var reg 1 % clk $end
$var reg 1 & cs $end
$var reg 2 ' mode [1:0] $end
$var reg 1 ( pass $end
$var reg 1 ) reset $end
$var reg 1 * sclk $end
$var reg 8 + test_nr [7:0] $end
$scope module spi_fsm_inst $end
$var wire 1 % clk $end
$var wire 1 & cs $end
$var wire 2 , mode [1:0] $end
$var wire 1 ) reset $end
$var wire 1 $ sample $end
$var wire 1 * sclk $end
$var wire 1 " shift $end
$var parameter 32 - CS $end
$var parameter 32 . FIRST1 $end
$var parameter 32 / FIRST3 $end
$var parameter 32 0 LAST1 $end
$var parameter 32 1 LAST3 $end
$var parameter 32 2 MODE $end
$var parameter 32 3 RESET $end
$var parameter 32 4 SAMPLE0 $end
$var parameter 32 5 SAMPLE1 $end
$var parameter 32 6 SAMPLE2 $end
$var parameter 32 7 SAMPLE3 $end
$var parameter 32 8 SHIFT0 $end
$var parameter 32 9 SHIFT1 $end
$var parameter 32 : SHIFT2 $end
$var parameter 32 ; SHIFT3 $end
$var parameter 32 < WAIT_HI0 $end
$var parameter 32 = WAIT_HI1 $end
$var parameter 32 > WAIT_HI2 $end
$var parameter 32 ? WAIT_HI3 $end
$var parameter 32 @ WAIT_LO0 $end
$var parameter 32 A WAIT_LO1 $end
$var parameter 32 B WAIT_LO2 $end
$var parameter 32 C WAIT_LO3 $end
$var reg 5 D state [4:0] $end
$var reg 5 E state_next [4:0] $end
$upscope $end
$scope module spi_fsm_ref_inst $end
$var wire 1 % clk $end
$var wire 1 & cs $end
$var wire 2 F mode [1:0] $end
$var wire 1 ) reset $end
$var wire 1 * sclk $end
$var parameter 32 G check_cs_hi $end
$var parameter 32 H first1 $end
$var parameter 32 I first3 $end
$var parameter 32 J last1 $end
$var parameter 32 K last3 $end
$var parameter 32 L mode_select $end
$var parameter 32 M rst $end
$var parameter 32 N sample0 $end
$var parameter 32 O sample1 $end
$var parameter 32 P sample2 $end
$var parameter 32 Q sample3 $end
$var parameter 32 R shift0 $end
$var parameter 32 S shift1 $end
$var parameter 32 T shift2 $end
$var parameter 32 U shift3 $end
$var parameter 32 V wait0hi $end
$var parameter 32 W wait0lo $end
$var parameter 32 X wait1hi $end
$var parameter 32 Y wait1lo $end
$var parameter 32 Z wait2hi $end
$var parameter 32 [ wait2lo $end
$var parameter 32 \ wait3hi $end
$var parameter 32 ] wait3lo $end
$var reg 1 # sample $end
$var reg 1 ! shift $end
$var reg 5 ^ state_nxt [4:0] $end
$var reg 5 _ state_r [4:0] $end
$upscope $end
$scope task finish_test $end
$upscope $end
$scope task test_evalutation $end
$upscope $end
$upscope $end
$enddefinitions $end
$comment Show the parameter values. $end
$dumpall
b1010 ]
b1110 \
b1001 [
b1101 Z
b111 Y
b1100 X
b1000 W
b1011 V
b10010 U
b10001 T
b10000 S
b1111 R
b10110 Q
b10101 P
b10100 O
b10011 N
b0 M
b10 L
b110 K
b101 J
b100 I
b11 H
b1 G
b1010 C
b1001 B
b111 A
b1000 @
b1110 ?
b1101 >
b1100 =
b1011 <
b10010 ;
b10001 :
b10000 9
b1111 8
b10110 7
b10101 6
b10100 5
b10011 4
b0 3
b10 2
b110 1
b101 0
b100 /
b11 .
b1 -
$end
#0
$dumpvars
b0 _
b1 ^
b0 F
b1 E
b0 D
b0 ,
b1 +
0*
1)
1(
b0 '
1&
1%
0$
0#
0"
0!
$end
#10
0%
#15
b1 E
b1 ^
1*
#20
1%
#30
b1 E
b1 ^
0%
0*
#40
b10 ^
b10 E
b1 _
b1 D
1%
0)
#45
b10 E
b10 ^
1*
#50
0%
#60
b1 E
b1 ^
1%
0*
0&
#70
0%
#75
1*
#80
1%
#90
b10 E
b10 ^
0%
0*
1&
#100
b10 D
b10 _
1%
#105
1*
#110
0%
#120
1%
0*
#130
b11 E
b11 ^
0%
0&
b1 '
b1 ,
b1 F
b10 +
#135
b10 E
b10 ^
1*
#140
1%
#150
b11 E
b11 ^
0%
0*
#160
b10 E
b10 ^
1%
1&
#165
1*
#170
0%
#180
1%
0*
#190
0%
#195
1*
#200
b1101 _
b1101 D
b1101 E
b1101 ^
1%
0&
b10 '
b10 ,
b10 F
b11 +
#210
b10101 E
b10101 ^
0%
0*
#220
1$
b1001 E
1#
b1001 ^
b10101 D
b10101 _
1%
#225
b1001 E
b1001 ^
1*
#230
b1001 E
b1001 ^
0%
1&
#240
0$
0#
b1001 _
b1001 D
b1001 E
b1001 ^
1%
0*
#250
0%
#255
b10001 E
b10001 ^
1*
#260
1"
b1101 E
1!
b1101 ^
b10001 D
b10001 _
1%
#270
b1101 E
b1101 ^
0%
0*
0&
b11 '
b11 ,
b11 F
b100 +
#280
0"
0!
b10101 ^
b10101 E
b1101 _
b1101 D
1%
#285
b1101 E
b1101 ^
1*
#290
0%
#300
b10 D
b10 _
b10 E
b10 ^
1%
0*
1&
#310
0%
#315
1*
#320
1%
#330
0%
0*
#340
b1 E
b1 ^
b0 D
b0 _
1%
1)
b101 +
#345
b1 E
b1 ^
1*
#350
0%
#360
b1 E
b1 ^
1%
0*
#370
0%
#375
b1 E
b1 ^
1*
#380
b1 D
b1 _
b1 E
b1 ^
1%
0*
0&
b0 '
b0 ,
b0 F
0)
#390
0%
1*
#400
1%
#405
0*
#410
0%
#420
1%
1*
#430
0%
#435
0*
#440
b10 _
b10 D
b10 E
b10 ^
1%
1&
#450
0%
1*
#460
1%
#465
0*
#470
0%
#480
b1 ^
b1 E
b0 _
b0 D
1%
1*
1)
b110 +
#490
0%
#495
b1 E
b1 ^
0*
#500
1%
#510
b1 E
b1 ^
0%
1*
#520
b1 _
b1 D
b1 E
b1 ^
1%
0&
b1 '
b1 ,
b1 F
0)
#525
0*
#530
0%
#540
1%
1*
#550
0%
#555
0*
#560
1%
1*
#570
0%
0*
#580
b10 D
b10 _
b10 E
b10 ^
1%
1&
#585
1*
#590
0%
#600
1%
0*
#610
0%
#615
1*
#620
1%
b111 +
