Exam_2024/2c/uart.v
module uart (
	input clk,
	input reset,
	input signal,
	output valid);

// define unique constants to identify each state
localparam BREAK = 4'd0;
localparam IDLE = 4'd1;
localparam START = 4'd2;
localparam BIT1 = 4'd3;
localparam BIT2 = 4'd4;
localparam BIT3 = 4'd5;
localparam BIT4 = 4'd6;
localparam BIT5 = 4'd7;
localparam BIT6 = 4'd8;
localparam BIT7 = 4'd9;
localparam BIT8 = 4'd10;
localparam STOP = 4'd11;

// declare verilog variables of type reg for use in always blocks
// <name>_r is used to infer a register in the clocked always block
// <name>_nxt is used assign the next state of the register in the combinational always block
reg [3 : 0] state_r, state_nxt;
reg valid_r, valid_nxt;

// clock synchronous always block will only be evaluated on the positive edge of the clock
// only use non-blocking assignments (<=) in this block
always @(posedge clk) begin
	// check for the reset signal on the clk edge, infering a synchronous reset
	// if the module is not being reset, assign all of the derived combinational <name>_nxt values to <name>_r
	// if the module is being reset, assign initial constant values to the <name>_r variables
	// this will infer a register for <name>_r if it is assigned defined values at all times
	// otherwise an unintentional latch will be inferred
	if (~reset) begin
		// module is not being reset
		// assign all of the derived combinational <name>_nxt values to the respective <name>_r
		state_r <= state_nxt;
		valid_r <= valid_nxt;
	end else begin
		// module is being reset
		// assign constant values to each <name>_r variable
		state_r <= BREAK;
		valid_r <= 1'b0;
	end
end

// combinational always block will evaluate whenever any signal in its sensitivity list changes
// here we use the wildcard * sensitivity list, which means that the list will be inferred from the assignments in the block
// only use blocking assignments (=) in this block
always @(*) begin
	// make sure that <name>_nxt signals are always defined to avoid latches
	// to ensure register elements minimally retain their last value, assign each <name>_nxt its respective <name>_r value
	state_nxt = state_r;
	valid_nxt = valid_r;

	// case statement is used to perform different logical derivations depending on current state
	// state_r stores the current state of this FSM
	// the unique state identifiers that were defined near the top of this file are used to identify the current state
	case (state_r)
		// state_r will remain constant between positive clock edges
		// only one unique state can match at any time
		BREAK: // evaluate logic for state BREAK
		begin
			valid_nxt = 1'b0;
			if (signal == 1'b1)
			begin
				state_nxt = IDLE;
			end
		end

		IDLE: // evaluate logic for state IDLE
		begin
			valid_nxt = 1'b0;
			if (signal == 1'b0)
			begin
				state_nxt = START;
			end
		end

		START: // evaluate logic for state START
		begin
			valid_nxt = 1'b0;
			state_nxt = BIT1;
		end

		BIT1: // evaluate logic for state BIT1
		begin
			valid_nxt = 1'b0;
			state_nxt = BIT2;
		end

		BIT2: // evaluate logic for state BIT2
		begin
			valid_nxt = 1'b0;
			state_nxt = BIT3;
		end

		BIT3: // evaluate logic for state BIT2
		begin
			valid_nxt = 1'b0;
			state_nxt = BIT4;
		end

		BIT4: // evaluate logic for state BIT4
		begin
			valid_nxt = 1'b0;
			state_nxt = BIT5;
		end

		BIT5: // evaluate logic for state BIT5
		begin
			valid_nxt = 1'b0;
			state_nxt = BIT6;
		end

		BIT6: // evaluate logic for state BIT6
		begin
			valid_nxt = 1'b0;
			state_nxt = BIT7;
		end

		BIT7: // evaluate logic for state BIT6
		begin
			valid_nxt = 1'b0;
			state_nxt = BIT8;
		end

		BIT8: // evaluate logic for state BIT7
		begin
			valid_nxt = 1'b0;
			if (signal == 1'b0)
			begin
				state_nxt = BREAK;
			end
			else if (signal == 1'b1)
			begin
				state_nxt = STOP;
			end
		end

		STOP: // evaluate logic for state STOP
		begin
			valid_nxt = 1'b1;
			if (signal == 1'b1)
			begin
				state_nxt = IDLE;
			end
			else if (signal == 1'b0)
			begin
				state_nxt = START;
			end
		end

		default: // should not be reachable if the state register is initialised and updated correctly
		begin
			valid_nxt = 1'b0;
			state_nxt = BREAK;
		end
	endcase
end

// assign values to output ports
assign valid = valid_r;

endmodule

Exam_2024/2c/src/uart_ref.v
module uart_ref (
	input clk,
	input reset,
	input signal,
	output valid);

// define unique constants to identify each state
localparam BREAK = 4'd0;
localparam IDLE = 4'd1;
localparam START = 4'd2;
localparam BIT1 = 4'd3;
localparam BIT2 = 4'd4;
localparam BIT3 = 4'd5;
localparam BIT4 = 4'd6;
localparam BIT5 = 4'd7;
localparam BIT6 = 4'd8;
localparam BIT7 = 4'd9;
localparam BIT8 = 4'd10;
localparam STOP = 4'd11;

// declare verilog variables of type reg for use in always blocks
// <name>_r is used to infer a register in the clocked always block
// <name>_nxt is used assign the next state of the register in the combinational always block
reg [3 : 0] state_r, state_nxt;
// reg valid_r, valid_nxt;

// clock synchronous always block will only be evaluated on the positive edge of the clock
// only use non-blocking assignments (<=) in this block
always @(posedge clk) begin
	// check for the reset signal on the clk edge, infering a synchronous reset
	// if the module is not being reset, assign all of the derived combinational <name>_nxt values to <name>_r
	// if the module is being reset, assign initial constant values to the <name>_r variables
	// this will infer a register for <name>_r if it is assigned defined values at all times
	// otherwise an unintentional latch will be inferred
	if (reset == 1'b0) begin
		// module is not being reset
		// assign all of the derived combinational <name>_nxt values to the respective <name>_r
		state_r <= state_nxt;
// 		valid_r <= valid_nxt;
	end else begin
		// module is being reset
		// assign constant values to each <name>_r variable
		state_r <= BREAK;
// 		valid_r <= 1'b0;
	end
end

// combinational always block will evaluate whenever any signal in its sensitivity list changes
// here we use the wildcard * sensitivity list, which means that the list will be inferred from the assignments in the block
// only use blocking assignments (=) in this block
always @(*) begin
	// make sure that <name>_nxt signals are always defined to avoid latches
	// to ensure register elements minimally retain their last value, assign each <name>_nxt its respective <name>_r value
	state_nxt = state_r;
// 	valid_nxt = valid_r;

	// case statement is used to perform different logical derivations depending on current state
	// state_r stores the current state of this FSM
	// the unique state identifiers that were defined near the top of this file are used to identify the current state
	case (state_r)
		// state_r will remain constant between positive clock edges
		// only one unique state can match at any time
		BREAK: // evaluate logic for state BREAK
		begin
// 			valid_nxt = 1'b0;
			if (signal == 1'b1)
			begin
				state_nxt = IDLE;
			end
		end

		IDLE: // evaluate logic for state IDLE
		begin
// 			valid_nxt = 1'b0;
			if (signal == 1'b0)
			begin
				state_nxt = START;
			end
		end

		START: // evaluate logic for state START
		begin
// 			valid_nxt = 1'b0;
			state_nxt = BIT1;
		end

		BIT1: // evaluate logic for state BIT1
		begin
// 			valid_nxt = 1'b0;
			state_nxt = BIT2;
		end

		BIT2: // evaluate logic for state BIT2
		begin
// 			valid_nxt = 1'b0;
			state_nxt = BIT3;
		end

        BIT3:
        begin
            // valid_nxt = 1'b0;
            state_nxt = BIT4;
        end

		BIT4: // evaluate logic for state BIT4
		begin
// 			valid_nxt = 1'b0;
			state_nxt = BIT5;
		end

		BIT5: // evaluate logic for state BIT5
		begin
// 			valid_nxt = 1'b0;
			state_nxt = BIT6;
		end

		BIT6: // evaluate logic for state BIT6
		begin
// 			valid_nxt = 1'b0;
			state_nxt = BIT7;
		end

		BIT7: // evaluate logic for state BIT7
		begin
// 			valid_nxt = 1'b0;
			state_nxt = BIT8;
		end
		
		BIT8:
		begin
		    if (signal == 1'b1)
		    begin
		      //  valid_nxt = 1'b1;
		        state_nxt = STOP;
		    end
		    else begin
		      //  valid_nxt = 1'b0;
		        state_nxt = BREAK;
		    end
	    end
		

		STOP: // evaluate logic for state STOP
		begin
// 			valid_nxt = 1'b0;
			if (signal == 1'b1)
			begin
				state_nxt = IDLE;
			end
			else if (signal == 1'b0)
			begin
				state_nxt = START;
			end
		end

		default: // should not be reachable if the state register is initialised and updated correctly
		begin
// 			valid_nxt = 1'b0;
			state_nxt = BREAK;
		end
    endcase
end

// assign values to output ports
assign valid = (state_r == STOP);

endmodule

Exam_2024/2c/src/Test_tb.v
`timescale 1ns/1ns
`include "uart.v"
`include "uart_ref.v"
// COMPILE THE CODE WITH THE FOLLOWING COMMAND:
// "iverilog -o compiled.vvp Test_tb.v"

// COMPILE THE SIMULATION WITH THE FOLLOWING COMMAND:
// "vvp compiled.vvp"

// SEE THE SIMULATION WITH THE FOLLOWING COMMAND:
// "gtkwave gtk_sim.vcd"

module Test_tb;

        reg clk = 0;
        reg reset = 0;
        reg signal = 0;

        wire valid;
        wire valid_ref;
                
        uart_ref uart_ref_inst(
		.clk(clk),
		.reset(reset),
		.signal(signal),
		.valid(valid_ref)
                );
        
        uart uart_inst(
		.clk(clk),
		.reset(reset),
		.signal(signal),
		.valid(valid)
                );
   
//      <<DECLARE CLOCK>>
        always #10 clk=~clk;
        
        initial begin
	        $dumpfile("src/gtk_sim.vcd");
   	        $dumpvars(0, Test_tb);

                $display("Test Bench Started!!!!!");

// 	  <<INITIALIZE INPUT SIGNALS>>
                clk = 1;
                reset = 0;
                signal = 0;
                        
// 	  <<RESET>>
                reset = 1;
                #40
                reset = 0;
                #20
                   
// 	  <<INPUT SEQUENCE>>
                signal = 1;
                #20
                signal = 0;
                #20  
                signal = 0;
                #20  
                signal = 1;
                #20  

// 	  <<RESET>>
                signal = 0;
                reset = 1;
                #40
                reset = 0;
                #20
                   
// 	  <<INPUT SEQUENCE>>
                signal = 1;
                #20
                signal = 0;
                #20  
                signal = 1;
                #20  
                signal = 0;
                #20   
                signal = 1;
                #20
                signal = 0;
                #20  
                signal = 1;
                #20  
                signal = 0;
                #20   

// 	  <<RESET>>
                signal = 0;
                reset = 1;
                #40
                reset = 0;
                #20
                   
// 	  <<INPUT SEQUENCE>>
                signal = 1;
                #20
                signal = 0;
                #20  
                signal = 0;
                #20  
                signal = 1;
                #20  
                signal = 0;
                #20  
                signal = 0;
                #20  
                signal = 0;
                #20  
                signal = 1;
                #20  
                signal = 1;
                #20  
                signal = 1;
                #20  
                signal = 1;
                #20  

// 	  <<RESET>>
                signal = 0;
                reset = 1;
                #40
                reset = 0;
                #20
                
//        <<Finish>>
                #60
                $finish;
        end


endmodule

Exam_2024/2c/src/gtk_sim.vcd
$date
	Tue Jul 23 00:33:09 2024
$end
$version
	Icarus Verilog
$end
$timescale
	1ns
$end
$scope module Test_tb $end
$var wire 1 ! valid_ref $end
$var wire 1 " valid $end
$var reg 1 # clk $end
$var reg 1 $ reset $end
$var reg 1 % signal $end
$scope module uart_inst $end
$var wire 1 # clk $end
$var wire 1 $ reset $end
$var wire 1 % signal $end
$var wire 1 " valid $end
$var parameter 4 & BIT1 $end
$var parameter 4 ' BIT2 $end
$var parameter 4 ( BIT3 $end
$var parameter 4 ) BIT4 $end
$var parameter 4 * BIT5 $end
$var parameter 4 + BIT6 $end
$var parameter 4 , BIT7 $end
$var parameter 4 - BIT8 $end
$var parameter 4 . BREAK $end
$var parameter 4 / IDLE $end
$var parameter 4 0 START $end
$var parameter 4 1 STOP $end
$var reg 4 2 state_nxt [3:0] $end
$var reg 4 3 state_r [3:0] $end
$var reg 1 4 valid_nxt $end
$var reg 1 5 valid_r $end
$upscope $end
$scope module uart_ref_inst $end
$var wire 1 # clk $end
$var wire 1 $ reset $end
$var wire 1 % signal $end
$var wire 1 ! valid $end
$var parameter 4 6 BIT1 $end
$var parameter 4 7 BIT2 $end
$var parameter 4 8 BIT3 $end
$var parameter 4 9 BIT4 $end
$var parameter 4 : BIT5 $end
$var parameter 4 ; BIT6 $end
$var parameter 4 < BIT7 $end
$var parameter 4 = BIT8 $end
$var parameter 4 > BREAK $end
$var parameter 4 ? IDLE $end
$var parameter 4 @ START $end
$var parameter 4 A STOP $end
$var reg 4 B state_nxt [3:0] $end
$var reg 4 C state_r [3:0] $end
$upscope $end
$upscope $end
$enddefinitions $end
$comment Show the parameter values. $end
$dumpall
b1011 A
b10 @
b1 ?
b0 >
b1010 =
b1001 <
b1000 ;
b111 :
b110 9
b101 8
b100 7
b11 6
b1011 1
b10 0
b1 /
b0 .
b1010 -
b1001 ,
b1000 +
b111 *
b110 )
b101 (
b100 '
b11 &
$end
#0
$dumpvars
b0 C
b0 B
05
04
b0 3
b0 2
0%
1$
1#
0"
0!
$end
#10
0#
#20
1#
#30
0#
#40
1#
0$
#50
0#
#60
b1 3
b1 C
b1 2
b1 B
1#
1%
#70
0#
#80
b10 C
b10 3
b11 2
b11 B
1#
0%
#90
0#
#100
b100 2
b100 B
b11 3
b11 C
1#
#110
0#
#120
b100 C
b100 3
b101 2
b101 B
1#
1%
#130
0#
#140
b0 3
b0 C
b0 2
b0 B
1#
1$
0%
#150
0#
#160
1#
#170
0#
#180
1#
0$
#190
0#
#200
b1 C
b1 3
b1 2
b1 B
1#
1%
#210
0#
#220
b10 3
b10 C
b11 2
b11 B
1#
0%
#230
0#
#240
b11 C
b11 3
b100 2
b100 B
1#
1%
#250
0#
#260
b100 3
b100 C
b101 2
b101 B
1#
0%
#270
0#
#280
b101 C
b101 3
b110 2
b110 B
1#
1%
#290
0#
#300
b110 3
b110 C
b111 2
b111 B
1#
0%
#310
0#
#320
b111 C
b111 3
b1000 2
b1000 B
1#
1%
#330
0#
#340
b1000 3
b1000 C
b1001 2
b1001 B
1#
0%
#350
0#
#360
b0 B
b0 2
b0 C
b0 3
1#
1$
#370
0#
#380
1#
#390
0#
#400
1#
0$
#410
0#
#420
b1 3
b1 C
b1 2
b1 B
1#
1%
#430
0#
#440
b10 C
b10 3
b11 2
b11 B
1#
0%
#450
0#
#460
b100 2
b100 B
b11 3
b11 C
1#
#470
0#
#480
b100 C
b100 3
b101 2
b101 B
1#
1%
#490
0#
#500
b101 3
b101 C
b110 2
b110 B
1#
0%
#510
0#
#520
b111 B
b111 2
b110 C
b110 3
1#
#530
0#
#540
b1000 2
b1000 B
b111 3
b111 C
1#
#550
0#
#560
b1000 C
b1000 3
b1001 2
b1001 B
1#
1%
#570
0#
#580
b1010 2
b1010 B
b1001 3
b1001 C
1#
#590
0#
#600
b1011 B
b1011 2
b1010 C
b1010 3
1#
#610
0#
#620
b1 2
14
b1 B
b1011 3
1!
b1011 C
1#
#630
0#
#640
0!
b0 C
b0 3
04
b0 2
b0 B
1#
1$
0%
#650
0#
#660
1#
#670
0#
#680
1#
0$
