Exam_2021/2e/counter.v
module counter (
    input clk,
    input reset,
    input tr,
    output cf,
    input mode);

    parameter t_value = 1;

    assign cf = tr;

endmodule

Exam_2021/2e/counter_ref.v
module counter_ref (
    input clk,
    input reset,
    input tr,
    output cf,
    input mode);

    parameter t_value = 5;

    reg state, state_next, out;
    parameter COUNTING = 0;
    parameter IDLE = 1;

    reg [15:0] delay, delay_next;
    reg [31:0] nr_clks, nr_clks_next;

    assign cf = (reset)?1:out;

    always @(posedge clk) begin
        if(reset) begin
            out <= 1;
            state <= IDLE;
            delay <= 0;
            nr_clks <= 0;
        end else begin 
            if (~state) begin
                out <= 0;
            end else begin
                out <= 1;
            end
            state <= state_next;
            delay <= delay_next;
            nr_clks <= nr_clks_next;
        end
    end

    always @(*) begin
        delay_next = delay;
        nr_clks_next = nr_clks;
        state_next = state;

        if(state == IDLE) begin
            if(tr) begin
                delay_next = (mode)?(t_value*3):t_value;
                nr_clks_next = 0;
                state_next = COUNTING;
            end
        end else begin 
            if(nr_clks == delay_next-2) begin
                delay_next = 0;
                nr_clks_next = 0;
                state_next = IDLE;
            end else begin
                nr_clks_next = 1 + nr_clks;
            end
        end
    end

endmodule

Exam_2021/2e/counter_tb.v
`timescale 1ns/1ns
`include "counter.v"
`include "counter_ref.v"
// COMPILE THE CODE WITH THE FOLLOWING COMMAND:
// "iverilog -o counter_tb.vvp counter_tb.v"

// COMPILE THE SIMULATION WITH THE FOLLOWING COMMAND:
// "vvp counter_tb.vvp"

// SEE THE SIMULATION WITH THE FOLLOWING COMMAND:
// "gtkwave"

module counter_tb;

        reg clk = 0;
        reg reset = 0;
        reg tr = 0;
        reg mode = 0;

        wire cf;
        wire cf_ref;

        counter_ref counter_ref_inst(
		.clk(clk),
		.reset(reset),
		.tr(tr),
		.cf(cf_ref),
		.mode(mode)
                );

                
        counter counter_inst(
		.clk(clk),
		.reset(reset),
		.tr(tr),
		.cf(cf),
		.mode(mode)
                );
   
//      <<DECLARE CLOCK>>
        always #10 clk=~clk;
           
        initial begin
	        $dumpfile("counter_tb.vcd");
   	        $dumpvars(0, counter_tb);

                $display("Test Bench Started!!!!!");
//      <<Reset>>
                #10
                reset = 1;
                #40

//      <<Input Sequence Mode = 0>>

                reset = 0;
                tr = 1;
                mode = 0;
                #20
                tr = 0;
                mode = 0;
                #120
                
//      <<Reset>>
                reset = 1;
                #40
                
//      <<Input Sequence Mode = 0>>

                reset = 0;
                tr = 1;
                mode = 1;
                #20
                tr = 0;
                mode = 0;
                #360

                $display("Test Bench Finished!!!!!");
	        #100
                $finish;
        end


endmodule

Exam_2021/2e/counter_tb.vcd
$date
	Sun Jun 30 15:18:05 2024
$end
$version
	Icarus Verilog
$end
$timescale
	1ns
$end
$scope module counter_tb $end
$var wire 1 ! cf_ref $end
$var wire 1 " cf $end
$var reg 1 # clk $end
$var reg 1 $ mode $end
$var reg 1 % reset $end
$var reg 1 & tr $end
$scope module counter_inst $end
$var wire 1 " cf $end
$var wire 1 # clk $end
$var wire 1 $ mode $end
$var wire 1 % reset $end
$var wire 1 & tr $end
$var parameter 32 ' t_value $end
$upscope $end
$scope module counter_ref_inst $end
$var wire 1 # clk $end
$var wire 1 $ mode $end
$var wire 1 % reset $end
$var wire 1 & tr $end
$var wire 1 ! cf $end
$var parameter 32 ( COUNTING $end
$var parameter 32 ) IDLE $end
$var parameter 32 * t_value $end
$var reg 16 + delay [15:0] $end
$var reg 16 , delay_next [15:0] $end
$var reg 32 - nr_clks [31:0] $end
$var reg 32 . nr_clks_next [31:0] $end
$var reg 1 / out $end
$var reg 1 0 state $end
$var reg 1 1 state_next $end
$upscope $end
$upscope $end
$enddefinitions $end
$comment Show the parameter values. $end
$dumpall
b101 *
b1 )
b0 (
b1 '
$end
#0
$dumpvars
x1
x0
x/
bx .
bx -
bx ,
bx +
0&
0%
0$
0#
0"
x!
$end
#10
11
b0 .
b0 ,
b0 -
b0 +
10
1/
1!
1%
1#
#20
0#
#30
1#
#40
0#
#50
b1 .
b101 +
00
01
b101 ,
1#
1"
1&
0%
#60
0#
#70
0!
b1 -
0/
b10 .
1#
0"
0&
#80
0#
#90
b11 .
b10 -
1#
#100
0#
#110
11
b0 .
b0 ,
b11 -
1#
#120
0#
#130
b0 -
b0 +
10
1#
#140
0#
#150
1!
1/
1#
#160
0#
#170
1#
#180
0#
#190
1#
1%
#200
0#
#210
1#
#220
0#
#230
b1 .
b1111 +
00
01
b1111 ,
1#
1$
1"
1&
0%
#240
0#
#250
0!
b1 -
0/
b10 .
1#
0$
0"
0&
#260
0#
#270
b11 .
b10 -
1#
#280
0#
#290
b100 .
b11 -
1#
#300
0#
#310
b101 .
b100 -
1#
#320
0#
#330
b110 .
b101 -
1#
#340
0#
#350
b111 .
b110 -
1#
#360
0#
#370
b1000 .
b111 -
1#
#380
0#
#390
b1001 .
b1000 -
1#
#400
0#
#410
b1010 .
b1001 -
1#
#420
0#
#430
b1011 .
b1010 -
1#
#440
0#
#450
b1100 .
b1011 -
1#
#460
0#
#470
b1101 .
b1100 -
1#
#480
0#
#490
11
b0 .
b0 ,
b1101 -
1#
#500
0#
#510
b0 -
b0 +
10
1#
#520
0#
#530
1!
1/
1#
