Resit_2024/2d/spi_parity_odd_fsm.v
module spi_parity_odd_fsm (
    input clk,
    input reset,
    input cs,
    input sample,
    input in,
    output parity_bit);

    parameter RESET = 'd0;
    parameter CHECK = 'd1;
    parameter CS = 'd2;
    parameter ODD = 'd3;
    parameter EVEN = 'd4;
    
    reg [2:0] state, state_next;
    reg parity_bit_r, parity_bit_next;
    
    // assign parity_bit = (in == 1)?0:parity_bit_r;
    assign parity_bit = parity_bit_next;
    
    always @(posedge clk) begin
        if(reset) begin
            state <= RESET;
            parity_bit_r <= 1;
        end else begin
            state <= state_next;
            parity_bit_r <= parity_bit_next;
        end
    end
    
    always @(*) begin
        state_next = state;
        parity_bit_next = parity_bit_r;
        
        // if (reset) begin
        //     state_next = RESET;
        //     parity_bit_next = 1;
        // end else begin
            case(state)
                RESET: begin
                    if(reset == 0) begin
                        state_next = CHECK;
                        parity_bit_next = 1;
                    end
                end
                
                CHECK: begin
                    if(cs == 1) begin
                        state_next = CS;
                    end
                end
                
                CS: begin
                    if(cs == 0 & sample == 1 & in == 1) begin
                        state_next = ODD;
                        parity_bit_next = 0;
                    end
                end
                
                ODD: begin
                    if(cs == 1) begin
                        state_next = CS;
                    end else if(cs == 0 & sample == 1 & in == 1) begin
                        state_next = EVEN;
                        parity_bit_next = 1;
                    end
                end
                
                EVEN: begin
                    if(cs == 1) begin
                        state_next = CS;
                    end else if(cs == 0 & sample == 1 & in == 1) begin
                        state_next = ODD;
                        parity_bit_next = 0;
                    end
                end
                
                default: begin
                    state_next = CHECK;
                    parity_bit_next = 1;
                end
            
            endcase
        
        // end
    end
endmodule

Resit_2024/2d/src/spi_parity_odd_fsm_ref.v
module spi_parity_odd_fsm_ref (
    input clk,
    input reset,
    input cs,
    input sample,
    input in,
    output parity_bit);

    parameter RESET = 'd0;
    parameter CHECK = 'd1;
    parameter CS = 'd2;
    parameter ODD = 'd3;
    parameter EVEN = 'd4;
    
    reg [2:0] state, state_next;
    reg parity_bit_r, parity_bit_next;
    
    // assign parity_bit = (in == 1)?0:parity_bit_r;
    assign parity_bit = parity_bit_next;
    
    always @(posedge clk) begin
        if(reset) begin
            state <= RESET;
            parity_bit_r <= 1;
        end else begin
            state <= state_next;
            parity_bit_r <= parity_bit_next;
        end
    end
    
    always @(*) begin
        state_next = state;
        parity_bit_next = parity_bit_r;
        
        // if (reset) begin
        //     state_next = RESET;
        //     parity_bit_next = 1;
        // end else begin
            case(state)
                RESET: begin
                    if(reset == 0) begin
                        state_next = CHECK;
                        parity_bit_next = 1;
                    end
                end
                
                CHECK: begin
                    if(cs == 1) begin
                        state_next = CS;
                    end
                end
                
                CS: begin
                    if(cs == 0 & sample == 1 & in == 1) begin
                        state_next = ODD;
                        parity_bit_next = 0;
                    end
                end
                
                ODD: begin
                    if(cs == 1) begin
                        state_next = CS;
                    end else if(cs == 0 & sample == 1 & in == 1) begin
                        state_next = EVEN;
                        parity_bit_next = 1;
                    end
                end
                
                EVEN: begin
                    if(cs == 1) begin
                        state_next = CS;
                    end else if(cs == 0 & sample == 1 & in == 1) begin
                        state_next = ODD;
                        parity_bit_next = 0;
                    end
                end
                
                default: begin
                    state_next = CHECK;
                    parity_bit_next = 1;
                end
            
            endcase
        
        // end
    end
endmodule

Resit_2024/2d/src/Test_tb.v
`timescale 1ns/1ns
`include "spi_parity_odd_fsm.v"
`include "spi_parity_odd_fsm_ref.v"
// COMPILE THE CODE WITH THE FOLLOWING COMMAND:
// "iverilog -o compiled.vvp Test_tb.v"

// COMPILE THE SIMULATION WITH THE FOLLOWING COMMAND:
// "vvp compiled.vvp"

// SEE THE SIMULATION WITH THE FOLLOWING COMMAND:
// "gtkwave gtk_sim.vcd"

module Test_tb;

        reg clk = 0;
        reg reset = 0;
        reg cs = 0;
        reg sample = 0;
        reg in = 0;

        wire parity_bit;
        wire parity_bit_ref;
                
        spi_parity_odd_fsm_ref spi_parity_odd_fsm_ref_inst(
		.clk(clk),
		.reset(reset),
                .cs(cs),
                .sample(sample),
                .in(in),
		.parity_bit(parity_bit_ref)
                );
                
        spi_parity_odd_fsm spi_parity_odd_fsm_inst(
		.clk(clk),
		.reset(reset),
                .cs(cs),
                .sample(sample),
                .in(in),
		.parity_bit(parity_bit)
                );

        // Check outputs at every positive edge of the clock
        reg pass = 1; // Indicator for whether outputs match across all cycles
        always @(posedge clk) begin
                if (parity_bit !== parity_bit_ref) begin
                        pass = 0;
                end
        end

        // Task to finish simulation and print result
        reg [7:0] test_nr = 'd1; // Indicator for whether outputs match across all cycles
        task test_evalutation();
                begin
                if (pass) begin
                        $display("->TEST %d: PASSED",test_nr);
                end else begin
                        $display("->TEST %d: FAILED",test_nr);
                        finish_test(); // Terminate the simulation early on failure
                end
                test_nr = test_nr + 'd1;
                end
        endtask

        // Task to finish simulation and print result
        task finish_test();
                begin
                if (pass) begin
                        $display("\nFINAL EVALUATION: PASSED\n");
                end else begin
                        $display("\nFINAL EVALUATION: FAILED\n");
                end
                #40;
                $display("Test Bench TERMINATED at time: %d [Ns].",$time);
                $finish;
                end
        endtask

        // Clock generation
        always #10 clk = ~clk;
        
        initial begin
	        $dumpfile("src/gtk_sim.vcd");
   	        $dumpvars(0, Test_tb);

                $display("Test Bench Started!!!!!");

// 	        <<INITIALIZE INPUT csS>>
                clk = 1;
                reset = 0;
                cs = 0;
                sample = 0;
                in = 0;
                        
// 	        <<RESET>>
                reset = 1; #40;
                reset = 0; #20;
                   
                   
// 	        <<TEST SEQUENCE 1:>>
// 	        <<INPUT 1: Simple CS High and Low with No Sample>>
                cs = 1;
                sample = 0;
                in = 0;
                #20;

                cs = 0; 
                sample = 0;
                in = 0; 
                #20;

        // <<INPUT 2: CS Low, Sample High, In High (Transition to ODD)>>
                cs = 0; 
                sample = 1;
                in = 1;
                #20;

        // <<INPUT 3: CS Low, Sample High, In High (Transition to EVEN)>>
                cs = 0;
                sample = 1;
                in = 1;
                #20;

        // <<INPUT 4: CS High (Back to CS state)>>
        cs = 1;
        sample = 0;
        in = 0;
        #20;

        // <<INPUT 5: CS Low, Sample High, In High (Transition back to ODD)>>
        cs = 0;
        sample = 1;
        in = 1;
        #20;

        // <<INPUT 6: Transition from ODD to EVEN and back to CS>>
        cs = 0;
        sample = 1;
        in = 1;
        #20;

        cs = 1;
        sample = 0;
        in = 0;
        #20;

        // <<INPUT 7: CS Low, Sample Low, In Low (Remain in CS)>>
        cs = 0;
        sample = 0;
        in = 0;
        #20;

        // <<INPUT 8: CS Low, Sample High, In Low (No Parity Change)>>
        cs = 0;
        sample = 1;
        in = 0;
        #20;
        
        test_evalutation();

        // <<RESET>>
    reset = 1; #40;
    reset = 0; #20;

    // <<NEW TEST SEQUENCE: Different Scenario>>
    // <<INPUT 1: CS Low, Sample Low, In High (No Transition, Remain in CS)>>
    cs = 0;
    sample = 0;
    in = 1;
    #20;

    // <<INPUT 2: CS Low, Sample High, In Low (No Parity Change, Remain in EVEN/ODD)>>
    cs = 0;
    sample = 1;
    in = 0;
    #20;

    // <<INPUT 3: CS High, Sample High, In Low (Should transition back to CS state)>>
    cs = 1;
    sample = 1;
    in = 0;
    #20;

    // <<INPUT 4: CS Low, Sample High, In High (Transition to ODD if in EVEN, or EVEN if in ODD)>>
    cs = 0;
    sample = 1;
    in = 1;
    #20;

    // <<INPUT 5: CS Low, Sample High, In Low (No Parity Change)>>
    cs = 0;
    sample = 1;
    in = 0;
    #20;

    // <<INPUT 6: CS Low, Sample High, In High (Force parity transition to EVEN/ODD)>>
    cs = 0;
    sample = 1;
    in = 1;
    #20;

    // <<INPUT 7: CS High, Sample Low, In High (Return to CS state)>>
    cs = 1;
    sample = 0;
    in = 1;
    #20;

    // <<INPUT 8: CS Low, Sample Low, In Low (No Parity Change, Remain in CS)>>
    cs = 0;
    sample = 0;
    in = 0;
    #20;

    test_evalutation();

//      <<<<FINISH>>>>
        finish_test();

        end
endmodule

Resit_2024/2d/src/gtk_sim.vcd
$date
	Fri Aug 16 22:03:53 2024
$end
$version
	Icarus Verilog
$end
$timescale
	1ns
$end
$scope module Test_tb $end
$var wire 1 ! parity_bit_ref $end
$var wire 1 " parity_bit $end
$var reg 1 # clk $end
$var reg 1 $ cs $end
$var reg 1 % in $end
$var reg 1 & pass $end
$var reg 1 ' reset $end
$var reg 1 ( sample $end
$var reg 8 ) test_nr [7:0] $end
$scope module spi_parity_odd_fsm_inst $end
$var wire 1 # clk $end
$var wire 1 $ cs $end
$var wire 1 % in $end
$var wire 1 " parity_bit $end
$var wire 1 ' reset $end
$var wire 1 ( sample $end
$var parameter 32 * CHECK $end
$var parameter 32 + CS $end
$var parameter 32 , EVEN $end
$var parameter 32 - ODD $end
$var parameter 32 . RESET $end
$var reg 1 / parity_bit_next $end
$var reg 1 0 parity_bit_r $end
$var reg 3 1 state [2:0] $end
$var reg 3 2 state_next [2:0] $end
$upscope $end
$scope module spi_parity_odd_fsm_ref_inst $end
$var wire 1 # clk $end
$var wire 1 $ cs $end
$var wire 1 % in $end
$var wire 1 ! parity_bit $end
$var wire 1 ' reset $end
$var wire 1 ( sample $end
$var parameter 32 3 CHECK $end
$var parameter 32 4 CS $end
$var parameter 32 5 EVEN $end
$var parameter 32 6 ODD $end
$var parameter 32 7 RESET $end
$var reg 1 8 parity_bit_next $end
$var reg 1 9 parity_bit_r $end
$var reg 3 : state [2:0] $end
$var reg 3 ; state_next [2:0] $end
$upscope $end
$scope task finish_test $end
$upscope $end
$scope task test_evalutation $end
$upscope $end
$upscope $end
$enddefinitions $end
$comment Show the parameter values. $end
$dumpall
b0 7
b11 6
b100 5
b10 4
b1 3
b0 .
b11 -
b100 ,
b10 +
b1 *
$end
#0
$dumpvars
b0 ;
b0 :
19
18
b0 2
b0 1
10
1/
b1 )
0(
1'
1&
0%
0$
1#
1"
1!
$end
#10
0#
#20
1#
#30
0#
#40
b1 :
b1 1
b1 2
b1 ;
1#
0'
#50
0#
#60
b10 1
b10 :
b10 2
b10 ;
1#
1$
#70
0#
#80
1#
0$
#90
0#
#100
00
b11 1
09
b11 :
1"
1/
b100 2
1!
18
b100 ;
1#
1%
1(
#110
0#
#120
0!
08
b11 ;
0"
0/
b11 2
19
b100 :
10
b100 1
1#
#130
0#
#140
b10 1
b10 :
1"
1/
b10 2
1!
18
b10 ;
1#
0%
0(
1$
#150
0#
#160
09
b11 :
00
b11 1
1"
1/
b100 2
1!
18
b100 ;
1#
1%
1(
0$
#170
0#
#180
0"
0/
b11 2
0!
08
b11 ;
10
b100 1
19
b100 :
1#
#190
0#
#200
b10 :
b10 1
1"
1/
b10 2
1!
18
b10 ;
1#
0%
0(
1$
#210
0#
#220
1#
0$
#230
0#
#240
1#
1(
#250
0#
#260
b0 2
b0 ;
b0 1
b0 :
1#
1'
b10 )
#270
0#
#280
1#
#290
0#
#300
b1 1
b1 :
b1 2
b1 ;
1#
0'
#310
0#
#320
1#
1%
0(
#330
0#
#340
1#
0%
1(
#350
0#
#360
b10 :
b10 1
b10 2
b10 ;
1#
1$
#370
0#
#380
00
b11 1
09
b11 :
1"
1/
b100 2
1!
18
b100 ;
1#
1%
0$
#390
0#
#400
0"
0/
b11 2
0!
08
b11 ;
1#
0%
#410
0#
#420
10
b100 1
19
b100 :
0"
0/
b11 2
0!
08
b11 ;
1#
1%
#430
0#
#440
b10 :
b10 1
1"
1/
b10 2
1!
18
b10 ;
1#
0(
1$
#450
0#
#460
1#
0%
0$
#470
0#
#480
1#
b11 )
